---
layout: page
meta-title: Lambas in Java 8
title: Looking at lambdas
slug: java-8-lambdas
excerpt_separator: <!--more-->
tags:
 - java
 - lambdas
 - functional
---

Investigating lambda implementation in Java 8.
----------------------------------------------

After attending the [London Scala Users Group][LSUG] session on the [seven things you should know about the JVM][seventhings]  wanted to see what Java 8 does with the new lambda expressions. Using the [javap][javap] command we can have a look at what the JVM is running for us. The code we're looking at is a simple threshold filter.
<!--more-->


<div id="social">
    <iframe id="gh-fork" src="http://ghbtns.com/github-btn.html?user=codingsteve&repo=bestcoders&type=fork" allowtransparency="true" frameborder="0" scrolling="0" width="55px" height="20px"></iframe>
    <a href="https://twitter.com/codingSteve" class="twitter-follow-button" data-show-count="false" data-lang="en">Follow @codingSteve</a>
    <a href="https://twitter.com/share" class="twitter-share-button" data-url="{{ post.url}}" data-via="codingSteve" data-lang="en">Tweet</a>
</div>


We're looking at some very [simple code][LAMBDASJAVA] to see what happens under the covers... 

{%highlight java linenos %}

  void filterUsingLambdas(final List<Integer>l) { 
    Stream<Integer> filtered = l.stream().filter(x -> x < 1);

    filtered.map(x -> {
        System.out.println(x);
        return x;
      }
    );
  }
{%endhighlight%}

{% highlight java  %}
 void filterUsingLambdas(java.util.List<java.lang.Integer>);
    Code:
       0: aload_1
       1: invokeinterface #2,  1   // InterfaceMethod java/util/List.stream:()Ljava/util/stream/Stream;
       6: invokedynamic #3,  0     // InvokeDynamic #0:test:()Ljava/util/function/Predicate;
      11: invokeinterface #4,  2   // InterfaceMethod java/util/stream/Stream.filter:(Ljava/util/function/Predicate;)Ljava/util/stream/Stream;
      16: astore_2
      17: aload_2
      18: invokedynamic #5,  0     // InvokeDynamic #1:apply:()Ljava/util/function/Function;
      23: invokeinterface #6,  2   // InterfaceMethod java/util/stream/Stream.map:(Ljava/util/function/Function;)Ljava/util/stream/Stream;
      28: pop
      29: return


{% endhighlight %}

One key thing to note is that there's no inner classes generated for this code unlike the scala version.

There looks to be some magic under line 11 during the call to ```filter``` and similarly under line 23 on the call to ```map```. Those two lines seem to hide a large number of instructions. So let's look at a version using a plain loop with an if check.

{%highlight java linenos %}


  void filterUsingIf(final List<Integer> l){
    final Integer threshold = new Integer(1);
    for (final Integer i : l ) {
      if (threshold.compareTo(i) < 0){
        System.out.println(i);
      }
    }
  }

{%endhighlight%}

{% highlight java%}

  void filterUsingIf(java.util.List<java.lang.Integer>);
    Code:
       0: new           #7                  // class java/lang/Integer
       3: dup
       4: iconst_1
       5: invokespecial #8                  // Method java/lang/Integer."<init>":(I)V
       8: astore_2
       9: aload_1
      10: invokeinterface #9,  1            // InterfaceMethod java/util/List.iterator:()Ljava/util/Iterator;
      15: astore_3
      16: aload_3
      17: invokeinterface #10,  1           // InterfaceMethod java/util/Iterator.hasNext:()Z
      22: ifeq          56
      25: aload_3
      26: invokeinterface #11,  1           // InterfaceMethod java/util/Iterator.next:()Ljava/lang/Object;
      31: checkcast     #7                  // class java/lang/Integer
      34: astore        4
      36: aload_2
      37: aload         4
      39: invokevirtual #12                 // Method java/lang/Integer.compareTo:(Ljava/lang/Integer;)I
      42: ifge          53
      45: getstatic     #13                 // Field java/lang/System.out:Ljava/io/PrintStream;
      48: aload         4
      50: invokevirtual #14                 // Method java/io/PrintStream.println:(Ljava/lang/Object;)V
      53: goto          16
      56: return
{% endhighlight %}

[seventhings]: http://www.meetup.com/london-scala/events/224738222/
[LSUG]: http://www.meetup.com/london-scala/
[javap]: http://docs.oracle.com/javase/7/docs/technotes/tools/windows/javap.html
[LAMBDASJAVA]: https://github.com/codingSteve/bestcoders/blob/master/src/main/java/bestcoders/Lambdas.java